Flask_Wings-0.5.dist-info/METADATA
Flask_Wings-0.5.dist-info/RECORD
Flask_Wings-0.5.dist-info/WHEEL
Flask_Wings-0.5.dist-info/top_level.txt
flask_wings/FlaskWings.py
flask_wings/__init__.py
flask_wings/version.py
flask_wings/views.py
flask_wings/templates/index.html
flask_wings/templates/login.html
