Metadata-Version: 2.1
Name: Flask-Wings
Version: 0.5
Summary: Boilerplate Flask extension.
Home-page: http://github.com/vmlaker/flask-wings
Author: Velimir Mlaker
Author-email: vel.i.mir.mlaker@gmail.com
License: MIT
Platform: any
Classifier: Framework :: Flask
Classifier: Topic :: Internet :: WWW/HTTP :: Dynamic Content
Classifier: Development Status :: 5 - Production/Stable
Classifier: License :: OSI Approved :: MIT License
Classifier: Programming Language :: Python
Classifier: Programming Language :: Python :: 2
Classifier: Programming Language :: Python :: 2.6
Classifier: Programming Language :: Python :: 2.7
Classifier: Programming Language :: Python :: 3
Classifier: Programming Language :: Python :: 3.4
Classifier: Programming Language :: Python :: 3.5
Classifier: Programming Language :: Python :: 3.6
Classifier: Environment :: Web Environment
Classifier: Intended Audience :: Developers
Classifier: Operating System :: OS Independent
Requires-Dist: Flask (==1.0.2)
